kuzukiri/__init__.py
kuzukiri/kuzukiri.cpython-39-darwin.so
kuzukiri-0.1.3.dist-info/AUTHORS
kuzukiri-0.1.3.dist-info/LICENSE
kuzukiri-0.1.3.dist-info/METADATA
kuzukiri-0.1.3.dist-info/WHEEL
kuzukiri-0.1.3.dist-info/top_level.txt
kuzukiri-0.1.3.dist-info/RECORD
