Metadata-Version: 2.1
Name: kuzukiri
Version: 0.1.3
License: MIT
Project-URL: Source Code, https://github.com/alinear-corp/kuzukiri
Project-URL: Documentation, https://alinear-corp.github.io/kuzukiri/
Keywords: NLP,Natural Language Processing,Text Segmentation,Python,Rust,Japanese,Preprocessing,Text Processing
Platform: Windows
Platform: Linux
Platform: macOS
License-File: LICENSE
License-File: AUTHORS
